dynflow/__init__.py
dynflow/config.py
dynflow/registry.py
dynflow-0.1.0.dist-info/METADATA
dynflow-0.1.0.dist-info/WHEEL
dynflow-0.1.0.dist-info/top_level.txt
dynflow-0.1.0.dist-info/RECORD
