Metadata-Version: 2.2
Name: dynflow
Version: 0.1.0
Summary: Add your description here
Requires-Python: >=3.11
Requires-Dist: pyyaml>=6.0.2
